Core/__init__.py
Core/logger.py
DBs/__init__.py
DBs/connect_to_hosts.py
DBs/mongodb_wizard.py
DBs/sql_wizard.py
Special/__init__.py
Special/data_class.py
Wrapper/__init__.py
Wrapper/basic.py
Kingfish-0.1.1.dist-info/LICENSE
Kingfish-0.1.1.dist-info/METADATA
Kingfish-0.1.1.dist-info/WHEEL
Kingfish-0.1.1.dist-info/top_level.txt
Kingfish-0.1.1.dist-info/RECORD
