Metadata-Version: 2.1
Name: Kingfish
Version: 0.1.1
Summary: My first published package
Home-page: https://github.com/Geulmaster/Kingfish
Author: Eyal Geulayev
Author-email: eyal.geulayev@gmail.com
License: MIT
Platform: UNKNOWN
Classifier: License :: OSI Approved :: MIT License
Classifier: Programming Language :: Python :: 3
Classifier: Programming Language :: Python :: 3.8
Requires-Python: >=3.6
Requires-Dist: pymongo
Requires-Dist: paramiko
Requires-Dist: psycopg2-binary
